README.md
setup.py
neuwon/__init__.py
neuwon/builder.py
neuwon.egg-info/PKG-INFO
neuwon.egg-info/SOURCES.txt
neuwon.egg-info/dependency_links.txt
neuwon.egg-info/requires.txt
neuwon.egg-info/top_level.txt
neuwon/mechanisms/__init__.py
neuwon/mechanisms/hh.py