Metadata-Version: 2.1
Name: neuwon
Version: 0.0.0
Summary: Neuroscience simulator
Home-page: UNKNOWN
Author: David McDougall
Author-email: dam1784@rit.edu
License: MIT License
